{"cameraMode":{"drawMode":0,"name":"Shaded","section":"Shading Mode"},"sceneLighting":true,"audioPlay":false,"sceneViewState":{"showFog":true,"showMaterialUpdate":false,"showSkybox":true,"showFlares":true,"showImageEffects":true,"showParticleSystems":true},"in2DMode":false,"pivot":{"x":10.258094787597657,"y":1.509973406791687,"z":3.9718215465545656},"rotation":{"x":0.059570327401161197,"y":0.4527633786201477,"z":-0.030333291739225389,"w":0.8891252875328064},"size":1.7485628128051758,"orthographic":false}